pynarrative/__init__.py
pynarrative/story.py
pynarrative-0.1.dist-info/METADATA
pynarrative-0.1.dist-info/WHEEL
pynarrative-0.1.dist-info/top_level.txt
pynarrative-0.1.dist-info/RECORD
