Metadata-Version: 2.1
Name: pynarrative
Version: 0.1
Summary: Una libreria per creare visualizzazioni narrative con Altair
Author: Roberto Olinto Barsotti
Author-email: robeolinto.barsotti@gmail.com
Classifier: Programming Language :: Python :: 3
Classifier: License :: OSI Approved :: MIT License
Classifier: Operating System :: OS Independent
Requires-Python: >=3.6
Requires-Dist: altair
